citrand/__init__.py
citrand/__main__.py
citrand/errors.py
citrand/py.typed
citrand/timeout.py
citrand/tui.py
citrand-0.1.0.dist-info/LICENSE
citrand-0.1.0.dist-info/METADATA
citrand-0.1.0.dist-info/WHEEL
citrand-0.1.0.dist-info/entry_points.txt
citrand-0.1.0.dist-info/RECORD
