Metadata-Version: 2.1
Name: citrand
Version: 0.1.0
Summary: PRNG manipulation aide for emulated Pokémon 3DS titles
Home-page: https://codeberg.org/ViteByte/citrand
License: GPLv3+
Author: Taylor Rodríguez
Requires-Python: >=3.10,<4.0
Classifier: Development Status :: 1 - Planning
Classifier: Environment :: Console
Classifier: Intended Audience :: End Users/Desktop
Classifier: License :: OSI Approved :: GNU General Public License v3 or later (GPLv3+)
Classifier: License :: Other/Proprietary License
Classifier: Natural Language :: English
Classifier: Programming Language :: Python :: 3
Classifier: Programming Language :: Python :: 3.10
Classifier: Programming Language :: Python :: 3.11
Classifier: Programming Language :: Python :: 3.12
Classifier: Programming Language :: Python :: 3 :: Only
Classifier: Programming Language :: Python :: Implementation :: CPython
Classifier: Typing :: Typed
Requires-Dist: typing-extensions (>=4.12.2,<5.0.0)
Project-URL: Repository, https://codeberg.org/ViteByte/citrand
